khamster/__init__.py
khamster/hamster.py
khamster-0.1.0.dist-info/METADATA
khamster-0.1.0.dist-info/WHEEL
khamster-0.1.0.dist-info/top_level.txt
khamster-0.1.0.dist-info/RECORD
